sphinx_autopages/__init__.py
sphinx_autopages/sphinx_autopages.py
sphinx_autopages-0.0.3.dist-info/LICENSE
sphinx_autopages-0.0.3.dist-info/METADATA
sphinx_autopages-0.0.3.dist-info/WHEEL
sphinx_autopages-0.0.3.dist-info/RECORD
