Metadata-Version: 2.1
Name: sphinx_autopages
Version: 0.0.3
Summary: sphinx autopages extension
Home-page: https://github.com/av8r/sphinx-autopages
License: BSD-3-Clause
Keywords: sphinx,extension
Author: Stephane ENGEL
Author-email: stephane.engel@gmail.com
Requires-Python: >=3.12,<4.0
Classifier: Development Status :: 4 - Beta
Classifier: Framework :: Sphinx :: Extension
Classifier: Intended Audience :: Developers
Classifier: License :: OSI Approved :: BSD License
Classifier: Programming Language :: Python :: 3
Classifier: Programming Language :: Python :: 3.12
Requires-Dist: sphinx
Project-URL: Repository, https://github.com/av8r/sphinx-autopages
